mcps/__init__.py
mcps/config.py
mcps/logs.py
mcps/server.py
mcps/prompts/__init__.py
mcps/prompts/file_prompts.py
mcps/resources/__init__.py
mcps/resources/doc_resource.py
mcps/resources/project_resource.py
mcps/resources/url_resource.py
mcps/tools/__init__.py
mcps/tools/internet_search.py
mcps/tools/perplexity_search.py
mseep_mcps-0.1.4.dist-info/METADATA
mseep_mcps-0.1.4.dist-info/WHEEL
mseep_mcps-0.1.4.dist-info/entry_points.txt
mseep_mcps-0.1.4.dist-info/RECORD
